odoo/addons/sale_purchase_secondary_unit/README.rst
odoo/addons/sale_purchase_secondary_unit/__init__.py
odoo/addons/sale_purchase_secondary_unit/__manifest__.py
odoo/addons/sale_purchase_secondary_unit/i18n/es.po
odoo/addons/sale_purchase_secondary_unit/i18n/sale_purchase_secondary_unit.pot
odoo/addons/sale_purchase_secondary_unit/models/__init__.py
odoo/addons/sale_purchase_secondary_unit/models/purchase_order_line.py
odoo/addons/sale_purchase_secondary_unit/models/sale_order.py
odoo/addons/sale_purchase_secondary_unit/models/stock_rule.py
odoo/addons/sale_purchase_secondary_unit/readme/CONTRIBUTORS.rst
odoo/addons/sale_purchase_secondary_unit/readme/DESCRIPTION.rst
odoo/addons/sale_purchase_secondary_unit/readme/USAGE.rst
odoo/addons/sale_purchase_secondary_unit/static/description/icon.png
odoo/addons/sale_purchase_secondary_unit/static/description/index.html
odoo/addons/sale_purchase_secondary_unit/tests/__init__.py
odoo/addons/sale_purchase_secondary_unit/tests/test_sale_purchase_secondary_unit.py
odoo_addon_sale_purchase_secondary_unit-15.0.1.0.4.dist-info/METADATA
odoo_addon_sale_purchase_secondary_unit-15.0.1.0.4.dist-info/WHEEL
odoo_addon_sale_purchase_secondary_unit-15.0.1.0.4.dist-info/top_level.txt
odoo_addon_sale_purchase_secondary_unit-15.0.1.0.4.dist-info/RECORD
