Metadata-Version: 2.1
Name: odoo-addon-sale_purchase_secondary_unit
Version: 15.0.1.0.4
Summary: Propagate sale secondary uom to purchase orders
Home-page: https://github.com/OCA/purchase-workflow
Author: Tecnativa, Odoo Community Association (OCA)
Author-email: support@odoo-community.org
License: AGPL-3
Classifier: Programming Language :: Python
Classifier: Framework :: Odoo
Classifier: Framework :: Odoo :: 15.0
Classifier: License :: OSI Approved :: GNU Affero General Public License v3
Classifier: Development Status :: 4 - Beta
Requires-Python: >=3.8
Requires-Dist: odoo-addon-purchase-order-secondary-unit<15.1dev,>=15.0dev
Requires-Dist: odoo-addon-sale-stock-secondary-unit<15.1dev,>=15.0dev
Requires-Dist: odoo<15.1dev,>=15.0a
